README.txt
setup.cfg
setup.py
docs/HISTORY.txt
docs/INSTALL.txt
docs/LICENSE.GPL
docs/LICENSE.txt
easyshop/__init__.py
easyshop.carts.egg-info/PKG-INFO
easyshop.carts.egg-info/SOURCES.txt
easyshop.carts.egg-info/dependency_links.txt
easyshop.carts.egg-info/entry_points.txt
easyshop.carts.egg-info/namespace_packages.txt
easyshop.carts.egg-info/not-zip-safe
easyshop.carts.egg-info/requires.txt
easyshop.carts.egg-info/top_level.txt
easyshop/carts/__init__.py
easyshop/carts/config.py
easyshop/carts/configure.zcml
easyshop/carts/interfaces.py
easyshop/carts/profiles.zcml
easyshop/carts/adapters/__init__.py
easyshop/carts/adapters/cart_management.py
easyshop/carts/adapters/configure.zcml
easyshop/carts/adapters/discounts_calculation.py
easyshop/carts/adapters/item_management.py
easyshop/carts/adapters/prices.py
easyshop/carts/adapters/taxes.py
easyshop/carts/ajax/__init__.py
easyshop/carts/ajax/cart.py
easyshop/carts/ajax/configure.zcml
easyshop/carts/browser/__init__.py
easyshop/carts/browser/added_to_cart.pt
easyshop/carts/browser/added_to_cart.py
easyshop/carts/browser/cart.pt
easyshop/carts/browser/cart.py
easyshop/carts/browser/carts_container.pt
easyshop/carts/browser/carts_container.py
easyshop/carts/browser/configure.zcml
easyshop/carts/content/__init__.py
easyshop/carts/content/cart.py
easyshop/carts/content/cart_item.py
easyshop/carts/content/carts_container.py
easyshop/carts/portlets/__init__.py
easyshop/carts/portlets/cart.pt
easyshop/carts/portlets/cart.py
easyshop/carts/portlets/configure.zcml
easyshop/carts/profiles/__init__.py
easyshop/carts/profiles/default/factorytool.xml
easyshop/carts/profiles/default/portlets.xml
easyshop/carts/profiles/default/types.xml
easyshop/carts/profiles/default/workflows.xml
easyshop/carts/profiles/default/types/Cart.xml
easyshop/carts/profiles/default/types/CartItem.xml
easyshop/carts/profiles/default/types/CartsContainer.xml
easyshop/carts/tests/__init__.py
easyshop/carts/tests/base.py
easyshop/carts/tests/testDocTests.py
easyshop/carts/viewlets/__init__.py
easyshop/carts/viewlets/cart.pt
easyshop/carts/viewlets/cart.py
easyshop/carts/viewlets/configure.zcml