Metadata-Version: 1.0
Name: easyshop.carts
Version: 0.1a1
Summary: Cart management for EasyShop
Home-page: http://iqpp.de
Author: Plone Foundation
Author-email: kai.diefenbach@iqpp.de
License: GPL
Platform: UNKNOWN
Classifier: Framework :: Plone
Classifier: Framework :: Zope2
Classifier: Framework :: Zope3
Classifier: Programming Language :: Python
Classifier: Topic :: Software Development :: Libraries :: Python Modules
